{"cameraMode":{"drawMode":0,"name":"Shaded","section":"Shading Mode"},"sceneLighting":true,"audioPlay":false,"sceneViewState":{"m_AlwaysRefresh":false,"showFog":true,"showSkybox":true,"showFlares":true,"showImageEffects":true,"showParticleSystems":true,"showVisualEffectGraphs":true,"m_FxEnabled":true},"in2DMode":false,"pivot":{"x":2.139346122741699,"y":0.9252490997314453,"z":-2.3543128967285158},"rotation":{"x":-0.061062127351760867,"y":0.9338048100471497,"z":-0.19348496198654176,"w":-0.29470086097717287},"size":10.0,"orthographic":false}